LICENSE
README.md
setup.py
carefree_ml.egg-info/PKG-INFO
carefree_ml.egg-info/SOURCES.txt
carefree_ml.egg-info/dependency_links.txt
carefree_ml.egg-info/requires.txt
carefree_ml.egg-info/top_level.txt
cfml/__init__.py
cfml/misc/__init__.py
cfml/misc/toolkit.py
cfml/misc/hpo/__init__.py
cfml/misc/hpo/base.py
cfml/misc/hpo/bo/__init__.py
cfml/misc/hpo/bo/core.py
cfml/misc/hpo/naive/__init__.py
cfml/misc/hpo/naive/core.py
cfml/misc/optim/__init__.py
cfml/misc/optim/bo/__init__.py
cfml/misc/optim/bo/acquisition.py
cfml/misc/optim/bo/model.py
cfml/misc/optim/bo/target_space.py
cfml/misc/optim/gd/__init__.py
cfml/misc/optim/gd/bases.py
cfml/misc/optim/gd/optimizers/__init__.py
cfml/misc/optim/gd/optimizers/adam.py
cfml/misc/optim/gd/optimizers/rmsprop.py
cfml/misc/optim/gd/optimizers/sgd.py
cfml/misc/param_utils/__init__.py
cfml/misc/param_utils/core.py
cfml/misc/param_utils/data_types.py
cfml/misc/param_utils/distributions.py
cfml/misc/param_utils/types.py
cfml/misc/param_utils/normalizers/__init__.py
cfml/misc/param_utils/normalizers/bases.py
cfml/misc/param_utils/normalizers/cube/__init__.py
cfml/misc/param_utils/normalizers/cube/core.py
cfml/models/__init__.py
cfml/models/bases.py
cfml/models/mixins.py
cfml/models/linear_model/__init__.py
cfml/models/linear_model/mixins.py
cfml/models/linear_model/linear_regression/__init__.py
cfml/models/linear_model/linear_regression/model.py
cfml/models/linear_model/linear_svm/__init__.py
cfml/models/linear_model/linear_svm/mixins.py
cfml/models/linear_model/linear_svm/svc.py
cfml/models/linear_model/linear_svm/svr.py
cfml/models/linear_model/logistic_regression/__init__.py
cfml/models/linear_model/logistic_regression/model.py
cfml/models/naive_bayes/__init__.py
cfml/models/naive_bayes/gaussian.py
cfml/models/naive_bayes/multinomial.py
cfml/models/neural_network/__init__.py
cfml/models/neural_network/fcnn_clf.py
cfml/models/neural_network/fcnn_reg.py
cfml/models/neural_network/mixins.py
cfml/models/neural_network/modules.py
cfml/models/poly/__init__.py
cfml/models/poly/model.py
cfml/models/svm/__init__.py
cfml/models/svm/kernel.py
cfml/models/svm/mixins.py
cfml/models/svm/svc.py
cfml/models/svm/svr.py