Metadata-Version: 2.1
Name: carefree-ml
Version: 0.1.2.1
Summary: Machine Learning algorithms implemented with numpy
Home-page: https://github.com/carefree0910/carefree-ml
Author: carefree0910
Author-email: syameimaru.saki@gmail.com
License: UNKNOWN
Download-URL: https://github.com/carefree0910/carefree-ml/archive/v0.1.2.1.tar.gz
Keywords: python machine-learning numpy
Platform: UNKNOWN
License-File: LICENSE
